QueenSolution/__init__.py
QueenSolution/src/QueenSolution.py
QueenSolution/src/__init__.py
QueenSolution-0.0.10.dist-info/LICENSE
QueenSolution-0.0.10.dist-info/METADATA
QueenSolution-0.0.10.dist-info/WHEEL
QueenSolution-0.0.10.dist-info/top_level.txt
QueenSolution-0.0.10.dist-info/RECORD
